blended_tiling/__init__.py
blended_tiling/tiling_module.py
blended_tiling/version.py
blended_tiling-0.0.1.dev6.dist-info/LICENSE
blended_tiling-0.0.1.dev6.dist-info/METADATA
blended_tiling-0.0.1.dev6.dist-info/WHEEL
blended_tiling-0.0.1.dev6.dist-info/top_level.txt
blended_tiling-0.0.1.dev6.dist-info/RECORD
